Metadata-Version: 2.1
Name: validatum
Version: 0.1.0
Summary:  Setup file for validatum. 
Home-page: https://github.com/StephenRicher/validata
Author: Stephen Richer
Author-email: stephen.richer@nhs.net
License: MIT
Platform: UNKNOWN
Classifier: Development Status :: 1 - Planning
Classifier: License :: OSI Approved :: MIT License
Classifier: Intended Audience :: Science/Research
Classifier: Intended Audience :: Healthcare Industry
Classifier: Topic :: Scientific/Engineering
Classifier: Programming Language :: Python :: 3
Classifier: Natural Language :: English
Requires-Python: >=3.7.0
License-File: LICENSE
